modelhub_autonomize/__init__.py
modelhub_autonomize/client.py
modelhub_autonomize/decorators.py
modelhub_autonomize/pipeline.py
tests/__init__.py
modelhub_autonomize-0.1.0.dist-info/METADATA
modelhub_autonomize-0.1.0.dist-info/WHEEL
modelhub_autonomize-0.1.0.dist-info/top_level.txt
modelhub_autonomize-0.1.0.dist-info/RECORD
